{
	"dialogue_pos": "left",
	"position": [
		160,
		30
	],
	"no_antialiasing": false,
	"scale": 1.25,
	"animations": [
		{
			"loop_name": "Guy Normal",
			"idle_offsets": [
				0,
				0
			],
			"idle_name": "Guy Normal",
			"anim": "normal",
			"loop_offsets": [
				0,
				0
			]
		},
		{
			"loop_name": "Guy Angry",
			"idle_offsets": [
				0,
				0
			],
			"idle_name": "Guy Angry",
			"anim": "angry",
			"loop_offsets": [
				0,
				0
			]
		},
		{
			"loop_name": "Guy Sad",
			"idle_offsets": [
				0,
				0
			],
			"idle_name": "Guy Sad",
			"anim": "sad",
			"loop_offsets": [
				0,
				0
			]
		}
	],
	"image": "guyDia"
}